pyguard/__init__.py
pyguard/decorators.py
pyguard/exceptions.py
pyguard/guard.py
pyguard/utils.py
pyguard/validators/__init__.py
pyguard/validators/base.py
pyguard/validators/collections.py
pyguard/validators/comparisons.py
pyguard/validators/strings.py
pyguard/validators/types.py
pyguard_args-0.2.0.dist-info/licenses/LICENSE
tests/__init__.py
tests/test_async.py
tests/test_edge_cases.py
tests/test_error_msg.py
tests/test_integration.py
tests/validators/__init__.py
tests/validators/test_collections.py
tests/validators/test_comparisons.py
tests/validators/test_strings.py
tests/validators/test_types.py
pyguard_args-0.2.0.dist-info/METADATA
pyguard_args-0.2.0.dist-info/WHEEL
pyguard_args-0.2.0.dist-info/top_level.txt
pyguard_args-0.2.0.dist-info/RECORD
