Metadata-Version: 2.4
Name: pyguard-args
Version: 0.2.0
Summary: A Python library for validating function arguments using decorators
Home-page: https://github.com/tadow-dev/pyguard
Author: Mateusz Jasinski
Author-email: Mateusz Jasinski <mateusz@jasinski.software>
Project-URL: Homepage, https://github.com/tadow-dev/pyguard
Project-URL: Issues, https://github.com/tadow-dev/pyguard/issues
Project-URL: Repository, https://github.com/tadow-dev/pyguard
Keywords: validation,decorator,arguments,type-checking
Classifier: Development Status :: 3 - Alpha
Classifier: Intended Audience :: Developers
Classifier: License :: OSI Approved :: MIT License
Classifier: Programming Language :: Python :: 3
Classifier: Programming Language :: Python :: 3.10
Classifier: Programming Language :: Python :: 3.11
Classifier: Programming Language :: Python :: 3.12
Requires-Python: >=3.10
License-File: LICENSE
Dynamic: author
Dynamic: home-page
Dynamic: license-file
Dynamic: requires-python
